pipelinehelper/__init__.py
pipelinehelper-0.7.8.dist-info/LICENSE
pipelinehelper-0.7.8.dist-info/WHEEL
pipelinehelper-0.7.8.dist-info/METADATA
pipelinehelper-0.7.8.dist-info/RECORD
