Metadata-Version: 2.1
Name: pipelinehelper
Version: 0.7.8
Summary: Swaps scikit pipeline elements but also supports grid parameter configurations.
License: GPL-3.0+
Author: Benjamin Murauer
Author-email: b.murauer@posteo.de
Requires-Python: >=3.6.1,<4.0.0
Classifier: License :: OSI Approved :: GNU General Public License v3 or later (GPLv3+)
Classifier: Programming Language :: Python :: 3
Classifier: Programming Language :: Python :: 3.7
Classifier: Programming Language :: Python :: 3.8
Requires-Dist: sklearn
